jrpyintroduction/__init__.py
jrpyintroduction/__version__.py
jrpyintroduction/data/csv_data.csv
jrpyintroduction/data/health_insurance.zip
jrpyintroduction/data/high_net_worth_motor_insurance.zip
jrpyintroduction/data/movies.zip
jrpyintroduction/data/tabsep_data.csv
jrpyintroduction/data/titanic.xlsx
jrpyintroduction/data/yeast.zip
jrpyintroduction/data.py
jrpyintroduction/data_raw/yeast/horton_nakai.tsv
jrpyintroduction/data_raw/yeast/uniprot.tsv
jrpyintroduction/get_numeric_list.py
jrpyintroduction/vignettes/practical1.pdf
jrpyintroduction/vignettes/practical2.pdf
jrpyintroduction/vignettes/practical3.pdf
jrpyintroduction/vignettes/practical4.pdf
jrpyintroduction/vignettes/solutions1.pdf
jrpyintroduction/vignettes/solutions2.pdf
jrpyintroduction/vignettes/solutions3.pdf
jrpyintroduction/vignettes/solutions4.pdf
jrpyintroduction/vignettes.py
jrpyintroduction/yeast.py
jrpyintroduction-0.3.7.dist-info/METADATA
jrpyintroduction-0.3.7.dist-info/WHEEL
jrpyintroduction-0.3.7.dist-info/RECORD
