Metadata-Version: 2.3
Name: jrpyintroduction
Version: 0.3.7
Summary: Jumping Rivers: Introduction to Python
Author: Jumping Rivers
Author-email: info@jumpingrivers.com
Requires-Python: >=3.9
Classifier: Programming Language :: Python :: 3
Classifier: Programming Language :: Python :: 3.9
Classifier: Programming Language :: Python :: 3.10
Classifier: Programming Language :: Python :: 3.11
Classifier: Programming Language :: Python :: 3.12
Classifier: Programming Language :: Python :: 3.13
Requires-Dist: matplotlib (>=3.5,<4.0)
Requires-Dist: numpy (>=1.23,<2.0)
Requires-Dist: openpyxl (>=3.0,<4.0)
Requires-Dist: pandas (>=1.4,<2.0)
Requires-Dist: tqdm (>=4.64.1,<5.0.0)
